ygclib/__init__.py
ygclib/utils.py
ygclib-0.1.21.dist-info/LICENSE
ygclib-0.1.21.dist-info/METADATA
ygclib-0.1.21.dist-info/WHEEL
ygclib-0.1.21.dist-info/top_level.txt
ygclib-0.1.21.dist-info/RECORD
